{
  "generated_at": "2026-01-30T15:58:39Z",
  "deals": [
    {
      "listing_id": "21ec3c8f42d25a4a",
      "source": "seed",
      "url": "https://www.realtor.ca/real-estate/29123637/15210-82-avenue-surrey",
      "title": "15210 82 Avenue, Surrey, BC",
      "address": "15210 82 Avenue",
      "city": "Surrey",
      "price": 0,
      "beds": null,
      "baths": null,
      "sqft": null,
      "bc_assessed_value": null,
      "dom_days": 0,
      "price_drop_30d_ratio": 0.0,
      "is_relist": false,
      "score": -5.0,
      "reasons": [
        "Missing price"
      ],
      "missing_price": true
    }
  ]
}